{
    "Amazon Reviews": {
        "use": false,
        "dataset_path": null,
        "loading_script": null,
        "extra_params": null
    },
    "Food Reviews": {
        "use": false,
        "dataset_path": null,
        "loading_script": null,
        "extra_params": null
    },
    "Twitter GOP Debate": {
        "use": false,
        "dataset_path": null,
        "loading_script": null,
        "extra_params": {
            "confidence_min": 0.0
        }
    },
    "IMDB": {
        "use": false,
        "dataset_path": null,
        "loading_script": null,
        "extra_params": null
    },
    "Sentiment140": {
        "use": false,
        "dataset_path": null,
        "loading_script": null,
        "extra_params": null
    },
    "Twitter Airline": {
        "use": false,
        "dataset_path": null,
        "loading_script": null,
        "extra_params": {
            "confidence_min": 0.0
        }
    }
}